{"Title": "Seventh Heaven", "Year": "1997", "Rated": "N/A", "Released": "31 Jul 1998", "Runtime": "88 min", "Genre": "Drama", "Director": "Beno\u00eet Jacquot", "Writer": "Beno\u00eet Jacquot, J\u00e9r\u00f4me Beaujour", "Actors": "Sandrine Kiberlain, Vincent Lindon, Fran\u00e7ois Berl\u00e9and, Francine Berg\u00e9", "Plot": "The slightly kleptomanic 29-year-old Mathilde is experiencing strange swoonings since a few days. There she encounters a mysterious doctor who treats her with hypnosis therapy. As she gets ...", "Language": "French", "Country": "France", "Awards": "3 nominations.", "Poster": "https://m.media-amazon.com/images/M/MV5BMTM3OTE4NTg3MV5BMl5BanBnXkFtZTcwMTE4MDIyMQ@@._V1_SX300.jpg", "Metascore": "N/A", "imdbRating": "6.5", "imdbVotes": "352", "imdbID": "tt0124115", "Type": "movie", "DVD": "16 Nov 1999", "BoxOffice": "N/A", "Production": "Zeitgeist Films", "Website": "N/A", "Response": "True", "InternetMovieDatabaseRating": "6.5/10", "RottenTomatoesRating": "57%", "MetacriticRating": "N/A"}