{"Title": "Faust", "Year": "2011", "Rated": "Not Rated", "Released": "15 Nov 2013", "Runtime": "140 min", "Genre": "Drama, Fantasy, Mystery", "Director": "Aleksandr Sokurov", "Writer": "Yuriy Arabov (book), Aleksandr Sokurov (screenplay), Marina Koreneva (screenplay), Johann Wolfgang von Goethe (play)", "Actors": "Johannes Zeiler, Anton Adasinsky, Isolda Dychauk, Georg Friedrich", "Plot": "A despairing scholar sells his soul to Satan in exchange for one night with a beautiful young woman.", "Language": "German", "Country": "Russia", "Awards": "15 wins & 25 nominations.", "Poster": "https://m.media-amazon.com/images/M/MV5BMTM4NDgwNjU4Ml5BMl5BanBnXkFtZTgwNzU2OTI1MDE@._V1_SX300.jpg", "Metascore": "65", "imdbRating": "6.6", "imdbVotes": "4,847", "imdbID": "tt1437357", "Type": "movie", "DVD": "24 Jun 2014", "BoxOffice": "$36,664", "Production": "Leisure Time Features", "Website": "N/A", "Response": "True", "InternetMovieDatabaseRating": "6.6/10", "RottenTomatoesRating": "65%", "MetacriticRating": "65/100"}