{"Title": "Three Billboards Outside Ebbing, Missouri", "Year": "2017", "Rated": "R", "Released": "01 Dec 2017", "Runtime": "115 min", "Genre": "Comedy, Crime, Drama", "Director": "Martin McDonagh", "Writer": "Martin McDonagh", "Actors": "Frances McDormand, Caleb Landry Jones, Kerry Condon, Sam Rockwell", "Plot": "THREE BILLBOARDS OUTSIDE EBBING, MISSOURI is a darkly comic drama from Academy Award winner Martin McDonagh (In Bruges). After months have passed without a culprit in her daughter's murder case, Mildred Hayes (Academy Award winner Frances McDormand) makes a bold move, painting three signs leading into her town with a controversial message directed at William Willoughby (Academy Award nominee Woody Harrelson), the town's revered chief of police. When his second-in-command Officer Dixon (Sam Rockwell), an immature mother's boy with a penchant for violence, gets involved, the battle between Mildred and Ebbing's law enforcement is only exacerbated.", "Language": "English", "Country": "UK, USA", "Awards": "Won 2 Oscars. Another 130 wins & 222 nominations.", "Poster": "https://m.media-amazon.com/images/M/MV5BMjI0ODcxNzM1N15BMl5BanBnXkFtZTgwMzIwMTEwNDI@._V1_SX300.jpg", "Metascore": "88", "imdbRating": "8.2", "imdbVotes": "382,103", "imdbID": "tt5027774", "Type": "movie", "DVD": "27 Feb 2018", "BoxOffice": "$52,000,189", "Production": "Fox Searchlight Pictures", "Website": "N/A", "Response": "True", "InternetMovieDatabaseRating": "8.2/10", "RottenTomatoesRating": "90%", "MetacriticRating": "88/100"}