{"Title": "The Sisters Brothers", "Year": "2018", "Rated": "R", "Released": "19 Oct 2018", "Runtime": "122 min", "Genre": "Crime, Drama, Western", "Director": "Jacques Audiard", "Writer": "Jacques Audiard (screenplay by), Thomas Bidegain (screenplay by), Patrick DeWitt (based on the book by)", "Actors": "John C. Reilly, Joaquin Phoenix, Jake Gyllenhaal, Riz Ahmed", "Plot": "Based on Patrick DeWitt's novel, The Sisters Brothers revolves around the colourfully named gold prospector Hermann Kermit Warm, who's being pursued across 1000 miles of 1850s Oregon desert to San Francisco by the notorious assassins Eli and Charlie Sisters. Except Eli is having a personal crisis and beginning to doubt the longevity of his chosen career. And Hermann might have a better offer.", "Language": "English", "Country": "France, Spain, Romania, Belgium, USA", "Awards": "10 wins & 20 nominations.", "Poster": "https://m.media-amazon.com/images/M/MV5BOTZmNTI1MzMtMGY0ZS00YTRlLWI4OTktYzE3YzZjZjJkNDVlXkEyXkFqcGdeQXVyMjM4NTM5NDY@._V1_SX300.jpg", "Metascore": "78", "imdbRating": "7.0", "imdbVotes": "44,328", "imdbID": "tt4971344", "Type": "movie", "DVD": "05 Feb 2019", "BoxOffice": "N/A", "Production": "Annapurna Pictures", "Website": "N/A", "Response": "True", "InternetMovieDatabaseRating": "7.0/10", "RottenTomatoesRating": "87%", "MetacriticRating": "78/100"}