{"Title": "Broadcast News", "Year": "1987", "Rated": "R", "Released": "25 Dec 1987", "Runtime": "133 min", "Genre": "Comedy, Drama, Romance", "Director": "James L. Brooks", "Writer": "James L. Brooks", "Actors": "William Hurt, Albert Brooks, Holly Hunter, Robert Prosky", "Plot": "Basket-case network news producer Jane Craig falls for new reporter Tom Grunnick, a pretty boy who represents the trend towards entertainment news she despises. Aaron Altman, a talented but plain correspondent, carries an unrequited torch for Jane. Sparks fly between the three as the network prepares for big changes, and both the news and Jane must decide between style and substance.", "Language": "English, Spanish, French, German", "Country": "USA", "Awards": "Nominated for 7 Oscars. Another 15 wins & 17 nominations.", "Poster": "https://m.media-amazon.com/images/M/MV5BN2E1ZmU5NDQtNjdlZC00Y2VhLTk2MWMtMmU0M2YyY2E3MTkyXkEyXkFqcGdeQXVyMTAwMzUyOTc@._V1_SX300.jpg", "Metascore": "84", "imdbRating": "7.2", "imdbVotes": "25,457", "imdbID": "tt0092699", "Type": "movie", "DVD": "05 Oct 1999", "BoxOffice": "N/A", "Production": "Twentieth Century Fox Home Entertainment", "Website": "N/A", "Response": "True", "InternetMovieDatabaseRating": "7.2/10", "RottenTomatoesRating": "98%", "MetacriticRating": "84/100"}