{"Title": "\u00c9xtasis", "Year": "1996", "Rated": "N/A", "Released": "16 Feb 1996", "Runtime": "93 min", "Genre": "Drama", "Director": "Mariano Barroso", "Writer": "Mariano Barroso, Joaqu\u00edn Oristrell", "Actors": "Javier Bardem, Federico Luppi, Silvia Munt, Daniel Guzm\u00e1n", "Plot": "Three friends, two young men and a young woman, are bored by the normal world of their parents and want to flee in order to start living somewhere else. Thus they make a pervert plan: rob their own families. After that they flee without any destination and without having really planned where to go to.", "Language": "Spanish", "Country": "Spain", "Awards": "1 win & 4 nominations.", "Poster": "https://m.media-amazon.com/images/M/MV5BMTU2MTM3MjEwOF5BMl5BanBnXkFtZTcwNDg0MzMzMQ@@._V1_SX300.jpg", "Metascore": "N/A", "imdbRating": "6.9", "imdbVotes": "605", "imdbID": "tt0118239", "Type": "movie", "DVD": "29 Jul 2008", "BoxOffice": "N/A", "Production": "N/A", "Website": "N/A", "Response": "True", "InternetMovieDatabaseRating": "6.9/10", "RottenTomatoesRating": "N/A", "MetacriticRating": "N/A"}