{"Title": "Paradiso: Seven Days with Seven Women", "Year": "2000", "Rated": "N/A", "Released": "19 Jul 2001", "Runtime": "103 min", "Genre": "Comedy", "Director": "Rudolf Thome", "Writer": "Rudolf Thome", "Actors": "Hanns Zischler, Cora Frost, Adriana Altaras, Irm Hermann", "Plot": "On the occasion of his 60th birthday, Adam organizes an extended celebration at his country home. In addition to his current wife and their young children, the guests are his previous wives, the few most important of his former lovers, and the son he has not seen in decades with his family.", "Language": "German", "Country": "Germany", "Awards": "1 win & 1 nomination.", "Poster": "https://m.media-amazon.com/images/M/MV5BMTk0NDU5NTA4MF5BMl5BanBnXkFtZTcwMTYzMjEzMQ@@._V1_SX300.jpg", "Metascore": "N/A", "imdbRating": "5.9", "imdbVotes": "65", "imdbID": "tt0234421", "Type": "movie", "DVD": "N/A", "BoxOffice": "N/A", "Production": "N/A", "Website": "N/A", "Response": "True", "InternetMovieDatabaseRating": "5.9/10", "RottenTomatoesRating": "N/A", "MetacriticRating": "N/A"}