{"Title": "K\u00e4rlekens br\u00f6d", "Year": "1953", "Rated": "N/A", "Released": "23 Oct 1953", "Runtime": "90 min", "Genre": "Drama, War", "Director": "Arne Mattsson", "Writer": "Volodja Semitjov, Peder Sj\u00f6gren (novel)", "Actors": "Folke Sundquist, Georg Rydeberg, Nils Hallberg, Lennart Lindberg", "Plot": "Four Swedish volunteer soldiers are trapped in Russia. In front of them lies the front with enemy outposts and patrols, behind them the enemy minefields. Hope to return to their own lines decreases each day. Corpses of fallen, \"dead of cold and hard as iron\", forms the macabre landmarks in the winter landscape. Nearby is a burnt Russian village.", "Language": "Russian, Swedish", "Country": "Sweden", "Awards": "1 nomination.", "Poster": "N/A", "Metascore": "N/A", "imdbRating": "6.2", "imdbVotes": "16", "imdbID": "tt0045979", "Type": "movie", "DVD": "N/A", "BoxOffice": "N/A", "Production": "N/A", "Website": "N/A", "Response": "True", "InternetMovieDatabaseRating": "6.2/10", "RottenTomatoesRating": "N/A", "MetacriticRating": "N/A"}