{"Title": "Parasite", "Year": "2019", "Rated": "R", "Released": "08 Nov 2019", "Runtime": "132 min", "Genre": "Comedy, Crime, Drama, Thriller", "Director": "Bong Joon Ho", "Writer": "Bong Joon Ho (story), Bong Joon Ho (screenplay), Jin Won Han (screenplay)", "Actors": "Kang-ho Song, Sun-kyun Lee, Yeo-jeong Jo, Woo-sik Choi", "Plot": "All unemployed, Ki-taek and his family take peculiar interest in the wealthy and glamorous Parks, as they ingratiate themselves into their lives and get entangled in an unexpected incident.", "Language": "Korean, English", "Country": "South Korea", "Awards": "Nominated for 6 Oscars. Another 199 wins & 183 nominations.", "Poster": "https://m.media-amazon.com/images/M/MV5BYWZjMjk3ZTItODQ2ZC00NTY5LWE0ZDYtZTI3MjcwN2Q5NTVkXkEyXkFqcGdeQXVyODk4OTc3MTY@._V1_SX300.jpg", "Metascore": "96", "imdbRating": "8.6", "imdbVotes": "193,674", "imdbID": "tt6751668", "Type": "movie", "DVD": "14 Jan 2020", "BoxOffice": "N/A", "Production": "NEON", "Website": "N/A", "Response": "True", "InternetMovieDatabaseRating": "8.6/10", "RottenTomatoesRating": "99%", "MetacriticRating": "96/100"}