{"Title": "Young Ahmed", "Year": "2019", "Rated": "N/A", "Released": "21 Feb 2020", "Runtime": "90 min", "Genre": "Drama", "Director": "Jean-Pierre Dardenne, Luc Dardenne", "Writer": "Jean-Pierre Dardenne (screenplay), Luc Dardenne (screenplay)", "Actors": "Idir Ben Addi, Olivier Bonnaud, Myriem Akheddiou, Victoria Bluck", "Plot": "A Belgian teenager hatches a plot to kill his teacher after embracing an extremist interpretation of the Quran.", "Language": "French, Arabic", "Country": "Belgium, France", "Awards": "3 wins & 2 nominations.", "Poster": "https://m.media-amazon.com/images/M/MV5BZmJiNzMzYWQtZmQ1OC00ZDlkLTljNTktMmMxM2JlNzA3NmZhXkEyXkFqcGdeQXVyMjI3NDAyNg@@._V1_SX300.jpg", "Metascore": "64", "imdbRating": "6.6", "imdbVotes": "1,329", "imdbID": "tt8359822", "Type": "movie", "DVD": "N/A", "BoxOffice": "N/A", "Production": "N/A", "Website": "N/A", "Response": "True", "InternetMovieDatabaseRating": "6.6/10", "RottenTomatoesRating": "N/A", "MetacriticRating": "64/100"}