{"Title": "One Potato, Two Potato", "Year": "1964", "Rated": "N/A", "Released": "10 Aug 1964", "Runtime": "83 min", "Genre": "Drama", "Director": "Larry Peerce", "Writer": "Orville H. Hampton, Raphael Hayes", "Actors": "Barbara Barrie, Bernie Hamilton, Richard Mulligan, Harry Bellaver", "Plot": "Study of interracial marriage in the 1960's. A white divorc\u00e9e falls in love with and marries an African-American man. When her ex-husband sues for custody of her child, arguing that a mixed...", "Language": "English", "Country": "USA", "Awards": "Nominated for 1 Oscar. Another 1 win & 3 nominations.", "Poster": "https://m.media-amazon.com/images/M/MV5BMDg5NmYyODktZTQyNi00MWRjLTk3NDctZWFkNTRmODc2ZTFlXkEyXkFqcGdeQXVyMTMxMTY0OTQ@._V1_SX300.jpg", "Metascore": "N/A", "imdbRating": "7.2", "imdbVotes": "545", "imdbID": "tt0058429", "Type": "movie", "DVD": "N/A", "BoxOffice": "N/A", "Production": "Cinema 5", "Website": "N/A", "Response": "True", "InternetMovieDatabaseRating": "7.2/10", "RottenTomatoesRating": "N/A", "MetacriticRating": "N/A"}