{"Title": "Don Segundo Sombra", "Year": "1969", "Rated": "UNRATED", "Released": "14 Aug 1969", "Runtime": "100 min", "Genre": "Drama", "Director": "Manuel Antin", "Writer": "Manuel Antin, Ricardo G\u00fciraldes (novel)", "Actors": "Adolfo G\u00fciraldes, Juan Carvalledo, Luis Manuel de la Cuesta, Luis Medina Castro", "Plot": "The story takes place in San Antonio de Areco, in the Argentina pampas. Fabio C\u00e1ceres remembers his childhood as an orphan and his youth working in the field, next to his godfather, Don Segundo Sombra, a solitary gaucho.", "Language": "Spanish", "Country": "Argentina", "Awards": "1 win & 1 nomination.", "Poster": "https://m.media-amazon.com/images/M/MV5BMjk4NjE2MTMyM15BMl5BanBnXkFtZTcwNTQ0MjkxMQ@@._V1_SX300.jpg", "Metascore": "N/A", "imdbRating": "6.5", "imdbVotes": "35", "imdbID": "tt0064246", "Type": "movie", "DVD": "N/A", "BoxOffice": "N/A", "Production": "N/A", "Website": "N/A", "Response": "True", "InternetMovieDatabaseRating": "6.5/10", "RottenTomatoesRating": "N/A", "MetacriticRating": "N/A"}