{"Title": "Monologue", "Year": "1973", "Rated": "N/A", "Released": "03 Sep 1973", "Runtime": "115 min", "Genre": "Drama", "Director": "Ilya Averbakh", "Writer": "Yevgeny Gabrilovich", "Actors": "Mikhail Gluzskiy, Margarita Terekhova, Marina Neyolova, Stanislav Lyubshin", "Plot": "Professor Sretenski is a scientist and director of a research center in Russia. He is separated from his wife and lives alone. His daughter, who lives with the mother, comes to his home, leaving her daughter with him. He raises his granddaughter, feeling a great affection for her.", "Language": "Russian", "Country": "Soviet Union", "Awards": "1 nomination.", "Poster": "https://m.media-amazon.com/images/M/MV5BNjVhYWFmY2YtNWEzMS00YmM3LWJjYWEtNmJkODFlOWQyMDhlXkEyXkFqcGdeQXVyMTc4MzI2NQ@@._V1_SX300.jpg", "Metascore": "N/A", "imdbRating": "7.4", "imdbVotes": "261", "imdbID": "tt0068963", "Type": "movie", "DVD": "N/A", "BoxOffice": "N/A", "Production": "N/A", "Website": "N/A", "Response": "True", "InternetMovieDatabaseRating": "7.4/10", "RottenTomatoesRating": "N/A", "MetacriticRating": "N/A"}