{"Title": "Kikujiro", "Year": "1999", "Rated": "PG-13", "Released": "26 May 2000", "Runtime": "122 min", "Genre": "Drama, Comedy", "Director": "Takeshi Kitano", "Writer": "Takeshi Kitano", "Actors": "Takeshi Kitano, Yusuke Sekiguchi, Kayoko Kishimoto, The Great Giday\u00fb", "Plot": "Brash, loudmouthed and opportunistic, Kikujiro hardly seems the ideal companion for little Masao who is determined to travel long distances to see the mother he has never met. Their excursion to the cycle races is the first of a series of adventures for the unlikely pair which soon turns out to be a whimsical journey of laughter and tears with a wide array of surprises and odd ball characters to meet along the way.", "Language": "Japanese", "Country": "Japan", "Awards": "4 wins & 4 nominations.", "Poster": "https://m.media-amazon.com/images/M/MV5BM2IyMzNkYzMtMmYzNC00MDFhLTkxN2EtNGNmMmQyMjY3NTg1XkEyXkFqcGdeQXVyOTcyNDU5MDA@._V1_SX300.jpg", "Metascore": "44", "imdbRating": "7.8", "imdbVotes": "17,538", "imdbID": "tt0199683", "Type": "movie", "DVD": "N/A", "BoxOffice": "N/A", "Production": "N/A", "Website": "N/A", "Response": "True", "InternetMovieDatabaseRating": "7.8/10", "RottenTomatoesRating": "N/A", "MetacriticRating": "44/100"}