{"Title": "The Berliner", "Year": "1948", "Rated": "PASSED", "Released": "31 Dec 1948", "Runtime": "80 min", "Genre": "Comedy, Musical", "Director": "Robert A. Stemmle", "Writer": "G\u00fcnter Neumann (story), G\u00fcnter Neumann (screenplay)", "Actors": "Gert Fr\u00f6be, Tatjana Sais, Ute Sielisch, Aribert W\u00e4scher", "Plot": "Told in the style of the German cabaret theatre, where both Gunther Neumann and Gert Frobe were important members, this is a balladeer's version of a serious plot with musical interludes. The year is 2050 and the audience is asked to look at a telecast of 'The Ancients\", from a century ago. Flashback to Germany, 1948, where Otto Normalverbraucher (Otto Averageman in the English-narrated version) is just returning from service in the German army during World War II. His experiences, told tongue-in-cheek, of the troubles that beset the average, law-abiding German citizen in post-war, war-torn destitute Germany and his awareness of the changes and problems are the bulk of the story.", "Language": "German, English", "Country": "Germany", "Awards": "Nominated for 1 BAFTA Film Award. Another 1 win & 1 nomination.", "Poster": "https://m.media-amazon.com/images/M/MV5BODg1M2ZkOGYtZmU2YS00OWJlLTljYTUtMTBhYTgzZjU1MjQxXkEyXkFqcGdeQXVyNzQzNDEyOQ@@._V1_SX300.jpg", "Metascore": "N/A", "imdbRating": "7.3", "imdbVotes": "106", "imdbID": "tt0040156", "Type": "movie", "DVD": "N/A", "BoxOffice": "N/A", "Production": "N/A", "Website": "N/A", "Response": "True", "InternetMovieDatabaseRating": "7.3/10", "RottenTomatoesRating": "N/A", "MetacriticRating": "N/A"}