{"Title": "Free Zone", "Year": "2005", "Rated": "NOT RATED", "Released": "07 Apr 2006", "Runtime": "90 min", "Genre": "Comedy, Drama", "Director": "Amos Gitai", "Writer": "Amos Gitai, Marie-Jose Sanselme", "Actors": "Natalie Portman, Hana Laslo, Hiam Abbass, Carmen Maura", "Plot": "Rebecca, a young American lady who has been living in Jerusalem for a while, suddenly breaks off her engagement with Julio, her Israeli fianc\u00e9. In a state of emotional shock she gets into a taxi and asks the diver to take her anywhere she likes but away from the place where she broke up. Although reluctant, Hanna, the driver lets her accompany her to Jordan's Free Zone where she is to meet \"The American\", her husband Moshe's Palestinian business partner. Once there, they realize \"The American\" is not there but a Palestinian woman named Leila offers them, after much bickering with Hanna, to take them to the oasis where \"The American\" lives...", "Language": "English, Hebrew, Arabic, Spanish", "Country": "Israel, Belgium, France, Spain", "Awards": "1 win & 6 nominations.", "Poster": "https://m.media-amazon.com/images/M/MV5BMTQ0Nzc2Mzk3OF5BMl5BanBnXkFtZTcwMTM1NDY0MQ@@._V1_SX300.jpg", "Metascore": "51", "imdbRating": "5.9", "imdbVotes": "2,622", "imdbID": "tt0441761", "Type": "movie", "DVD": "29 May 2007", "BoxOffice": "N/A", "Production": "New Yorker Films", "Website": "N/A", "Response": "True", "InternetMovieDatabaseRating": "5.9/10", "RottenTomatoesRating": "26%", "MetacriticRating": "51/100"}