{"Title": "Nespokoen pat", "Year": "1955", "Rated": "N/A", "Released": "23 May 1955", "Runtime": "116 min", "Genre": "Drama", "Director": "Dako Dakovski", "Writer": "Stoyan Tz. Daskalov (novel)", "Actors": "Ivan Bratanov, Tzvetana Nikolova, Georgi Georgiev-Getz, Stefan Savov", "Plot": "The comparatively comfortable peasant Mito reluctantly parts with his land, which becomes collective property. He is not prepared to face the changes, which are taking place in the new Bulgarian village. One night he steals his oxen from the cooperative farm and thus comes into conflict with the whole village, even with his own wife. Tormented by loneliness, Mito uncertainly wins back his affection of his wife, the closeness of his children and friends. He thus arrives at the actual meaning of collective work and becomes a member of the collective farm.", "Language": "Bulgarian", "Country": "Bulgaria", "Awards": "1 nomination.", "Poster": "https://m.media-amazon.com/images/M/MV5BNDA0MDY4Y2EtODFkMC00OTlhLThmNGMtYjg5ZTIyMWYyNDUyXkEyXkFqcGdeQXVyMzg1OTY0NjI@._V1_SX300.jpg", "Metascore": "N/A", "imdbRating": "N/A", "imdbVotes": "N/A", "imdbID": "tt0253307", "Type": "movie", "DVD": "N/A", "BoxOffice": "N/A", "Production": "N/A", "Website": "N/A", "Response": "True", "InternetMovieDatabaseRating": "N/A", "RottenTomatoesRating": "N/A", "MetacriticRating": "N/A"}