{"Title": "The Eighth Day of the Week", "Year": "1958", "Rated": "N/A", "Released": "01 Aug 1983", "Runtime": "83 min", "Genre": "Drama, Romance", "Director": "Aleksander Ford", "Writer": "Aleksander Ford, Marek Hlasko (story and screenplay)", "Actors": "Sonja Ziemann, Zbigniew Cybulski, Barbara Polomska, Ilse Steppat", "Plot": "A young couple in love hopes to have some privacy but the widespread housing problems don't allow them to find any place to stay.", "Language": "Polish", "Country": "Poland, West Germany", "Awards": "1 nomination.", "Poster": "https://m.media-amazon.com/images/M/MV5BODdkNDI4ZDgtMTQyOS00YmY4LTllZmItMjQzOGQyYzhiNjUyXkEyXkFqcGdeQXVyMzg1ODEwNQ@@._V1_SX300.jpg", "Metascore": "N/A", "imdbRating": "6.9", "imdbVotes": "107", "imdbID": "tt0052036", "Type": "movie", "DVD": "N/A", "BoxOffice": "N/A", "Production": "N/A", "Website": "N/A", "Response": "True", "InternetMovieDatabaseRating": "6.9/10", "RottenTomatoesRating": "N/A", "MetacriticRating": "N/A"}