{"Title": "The Morning", "Year": "1967", "Rated": "N/A", "Released": "05 Jul 1967", "Runtime": "95 min", "Genre": "Drama, War", "Director": "Mladomir 'Purisa' Djordjevic", "Writer": "Mladomir 'Purisa' Djordjevic", "Actors": "Ljubisa Samardzic, Neda Arneric, Milena Dravic, Mija Aleksic", "Plot": "The war has ended leaving a deep trace in people. Going trough a different conflicts in the first days of peace - dealing with a former enemy's collaborators and executing traitors - a former soldier continues with killing even in peace. So, the war goes on, a struggle within himself and with the people around him.", "Language": "Serbo-Croatian", "Country": "Yugoslavia", "Awards": "4 wins & 1 nomination.", "Poster": "https://m.media-amazon.com/images/M/MV5BOGQyZDYwODYtYmIyNy00Y2NjLTg2ZjktMDBiZWUyMzVjYTIyXkEyXkFqcGdeQXVyNjUzNzQ4NDQ@._V1_SX300.jpg", "Metascore": "N/A", "imdbRating": "7.0", "imdbVotes": "130", "imdbID": "tt0061854", "Type": "movie", "DVD": "N/A", "BoxOffice": "N/A", "Production": "N/A", "Website": "N/A", "Response": "True", "InternetMovieDatabaseRating": "7.0/10", "RottenTomatoesRating": "N/A", "MetacriticRating": "N/A"}